server/__init__.py
server/decorate.py
server/metaclasses.py
server/port_descriptor.py
server/server_db.py
server/server_v1.py
server/log/__init__.py
server/log/client_log_config.py
server/log/server_log_config.py
server/server_utilit/__init__.py
server/server_utilit/config_win.py
server/server_utilit/del_user.py
server/server_utilit/history_users.py
server/server_utilit/list_users.py
server/server_utilit/main_win.py
server/server_utilit/reg_user.py
server/server_utilit/server.py
server/server_utilit/server_messeger.py
server/unit_tests/__init__.py
server/unit_tests/test_client.py
server/unit_tests/test_for_test.py
server/unit_tests/test_server.py
sents_server_chat-1.0.dist-info/METADATA
sents_server_chat-1.0.dist-info/WHEEL
sents_server_chat-1.0.dist-info/top_level.txt
sents_server_chat-1.0.dist-info/RECORD
