Metadata-Version: 2.1
Name: sents-server-chat
Version: 1.0
Summary: Server packet
Author: Slav Senteryov
Author-email: ricar@mail.ru
